{
    "Standorte":[
        {
            "ID": 1,
            "StandortName": "Fluhmatt"
        },
        {
            "ID": 2,
            "StandortName": "Röslimatt"
        }
    ],
    "Stockwerke":[
        {
            "ID": 1,
            "StockwerkName": "Stockwerk 1"
        },
        {
            "ID": 2,
            "StockwerkName": "Stockwerk 2"
        },
        {
            "ID": 3,
            "StockwerkName": "Stockwerk 3"
        },
        {
            "ID": 4,
            "StockwerkName": "Stockwerk 4"
        },
        {
            "ID": 5,
            "StockwerkName": "Stockwerk 5"
        }
    ]
}
